{"data": [{"numAutomate": 1, "cuveTemp": 3.4, "outsideTemp": 12.9, "weightCuveMilk": 10.6, "weightFinalProduct": 3809, "ph": 6.8, "kp": 41, "naCl": 1.5, "bactSalmo": 32, "bactEcoli": 41, "bactListeria": 43}, {"numAutomate": 2, "cuveTemp": 3.4, "outsideTemp": 9.8, "weightCuveMilk": 11.2, "weightFinalProduct": 4334, "ph": 7.1, "kp": 43, "naCl": 1.3, "bactSalmo": 27, "bactEcoli": 49, "bactListeria": 42}, {"numAutomate": 3, "cuveTemp": 3.0, "outsideTemp": 8.7, "weightCuveMilk": 11.2, "weightFinalProduct": 4183, "ph": 7.2, "kp": 36, "naCl": 1.6, "bactSalmo": 17, "bactEcoli": 42, "bactListeria": 42}, {"numAutomate": 4, "cuveTemp": 3.4, "outsideTemp": 10.1, "weightCuveMilk": 11.8, "weightFinalProduct": 4296, "ph": 7.0, "kp": 46, "naCl": 1.1, "bactSalmo": 32, "bactEcoli": 48, "bactListeria": 53}, {"numAutomate": 5, "cuveTemp": 3.3, "outsideTemp": 11.4, "weightCuveMilk": 11.7, "weightFinalProduct": 4529, "ph": 6.8, "kp": 37, "naCl": 1.4, "bactSalmo": 28, "bactEcoli": 42, "bactListeria": 45}, {"numAutomate": 6, "cuveTemp": 2.7, "outsideTemp": 8.4, "weightCuveMilk": 11.1, "weightFinalProduct": 4193, "ph": 7.0, "kp": 39, "naCl": 1.3, "bactSalmo": 22, "bactEcoli": 36, "bactListeria": 49}, {"numAutomate": 7, "cuveTemp": 3.4, "outsideTemp": 12.3, "weightCuveMilk": 8.8, "weightFinalProduct": 4043, "ph": 7.2, "kp": 40, "naCl": 1.6, "bactSalmo": 17, "bactEcoli": 41, "bactListeria": 45}, {"numAutomate": 8, "cuveTemp": 3.5, "outsideTemp": 11.8, "weightCuveMilk": 9.2, "weightFinalProduct": 4041, "ph": 7.2, "kp": 42, "naCl": 1.1, "bactSalmo": 36, "bactEcoli": 48, "bactListeria": 47}, {"numAutomate": 9, "cuveTemp": 3.3, "outsideTemp": 13.2, "weightCuveMilk": 10.0, "weightFinalProduct": 4571, "ph": 7.2, "kp": 45, "naCl": 1.1, "bactSalmo": 17, "bactEcoli": 39, "bactListeria": 50}, {"numAutomate": 10, "cuveTemp": 3.9, "outsideTemp": 8.6, "weightCuveMilk": 10.4, "weightFinalProduct": 3949, "ph": 7.2, "kp": 38, "naCl": 1.5, "bactSalmo": 26, "bactEcoli": 42, "bactListeria": 32}], "title": "paramunite_1_1635087689.6830704.json"}