{"data": [{"numAutomate": 1, "cuveTemp": 3.6, "outsideTemp": 12.6, "weightCuveMilk": 13.8, "weightFinalProduct": 3838, "ph": 6.9, "kp": 42, "naCl": 1.4, "bactSalmo": 20, "bactEcoli": 47, "bactListeria": 37}, {"numAutomate": 2, "cuveTemp": 3.7, "outsideTemp": 10.0, "weightCuveMilk": 8.7, "weightFinalProduct": 4191, "ph": 7.0, "kp": 41, "naCl": 1.5, "bactSalmo": 17, "bactEcoli": 49, "bactListeria": 54}, {"numAutomate": 3, "cuveTemp": 2.7, "outsideTemp": 13.4, "weightCuveMilk": 13.1, "weightFinalProduct": 4495, "ph": 6.8, "kp": 36, "naCl": 1.2, "bactSalmo": 22, "bactEcoli": 38, "bactListeria": 45}, {"numAutomate": 4, "cuveTemp": 2.7, "outsideTemp": 13.5, "weightCuveMilk": 11.0, "weightFinalProduct": 3867, "ph": 7.0, "kp": 42, "naCl": 1.5, "bactSalmo": 32, "bactEcoli": 42, "bactListeria": 35}, {"numAutomate": 5, "cuveTemp": 2.6, "outsideTemp": 11.3, "weightCuveMilk": 13.3, "weightFinalProduct": 3542, "ph": 7.1, "kp": 38, "naCl": 1.7, "bactSalmo": 26, "bactEcoli": 43, "bactListeria": 37}, {"numAutomate": 6, "cuveTemp": 3.6, "outsideTemp": 8.2, "weightCuveMilk": 13.7, "weightFinalProduct": 4305, "ph": 6.9, "kp": 43, "naCl": 1.3, "bactSalmo": 17, "bactEcoli": 43, "bactListeria": 54}, {"numAutomate": 7, "cuveTemp": 3.2, "outsideTemp": 12.9, "weightCuveMilk": 13.3, "weightFinalProduct": 3664, "ph": 7.1, "kp": 40, "naCl": 1.3, "bactSalmo": 27, "bactEcoli": 39, "bactListeria": 42}, {"numAutomate": 8, "cuveTemp": 3.5, "outsideTemp": 11.7, "weightCuveMilk": 11.4, "weightFinalProduct": 4264, "ph": 7.0, "kp": 39, "naCl": 1.7, "bactSalmo": 32, "bactEcoli": 38, "bactListeria": 28}, {"numAutomate": 9, "cuveTemp": 3.7, "outsideTemp": 9.3, "weightCuveMilk": 12.5, "weightFinalProduct": 4292, "ph": 7.0, "kp": 41, "naCl": 1.2, "bactSalmo": 36, "bactEcoli": 41, "bactListeria": 36}, {"numAutomate": 10, "cuveTemp": 3.8, "outsideTemp": 10.1, "weightCuveMilk": 11.5, "weightFinalProduct": 4381, "ph": 6.8, "kp": 46, "naCl": 1.1, "bactSalmo": 36, "bactEcoli": 45, "bactListeria": 43}], "title": "paramunite_1_1636718918.780658.json"}